pomodoro.py
pomodoro_multiplatform-1.0.5.dist-info/licenses/LICENSE
pomodoro_multiplatform-1.0.5.dist-info/METADATA
pomodoro_multiplatform-1.0.5.dist-info/WHEEL
pomodoro_multiplatform-1.0.5.dist-info/entry_points.txt
pomodoro_multiplatform-1.0.5.dist-info/top_level.txt
pomodoro_multiplatform-1.0.5.dist-info/RECORD
