Metadata-Version: 2.4
Name: pomodoro-multiplatform
Version: 1.0.5
Summary: A simple cross-platform Pomodoro timer with desktop notifications
Author-email: Rito0421 <y.namba0421@gmail.com>
License: MIT
Project-URL: Homepage, https://github.com/Rito0421/pomodoro
Project-URL: Repository, https://github.com/Rito0421/pomodoro
Project-URL: Issues, https://github.com/Rito0421/pomodoro/issues
Keywords: pomodoro,timer,productivity,cli
Classifier: Development Status :: 4 - Beta
Classifier: Intended Audience :: End Users/Desktop
Classifier: License :: OSI Approved :: MIT License
Classifier: Programming Language :: Python :: 3
Classifier: Programming Language :: Python :: 3.8
Classifier: Programming Language :: Python :: 3.9
Classifier: Programming Language :: Python :: 3.10
Classifier: Programming Language :: Python :: 3.11
Classifier: Programming Language :: Python :: 3.12
Classifier: Operating System :: OS Independent
Classifier: Topic :: Office/Business :: Scheduling
Requires-Python: >=3.8
License-File: LICENSE
Requires-Dist: plyer>=2.0.0
Provides-Extra: macos
Requires-Dist: pyobjus>=1.2.0; extra == "macos"
Provides-Extra: dev
Requires-Dist: pytest>=7.0.0; extra == "dev"
Requires-Dist: ruff>=0.1.0; extra == "dev"
Requires-Dist: mypy>=1.0.0; extra == "dev"
Dynamic: license-file
